Workbook

Sheet Raw_Data
A1: CustomerID | B1: Gender | C1: Age | D1: City | E1: ProductCategory | F1: Quantity | G1: Price | H1: TotalAmount | I1: PurchaseDate | J1: PaymentMethod | K1: CalculatedTotal | L1: validation | M1: age group | N1: TransactionType | O1: month | Q1: total revenue | R1: Male Revenue | S1: female revenu | V1: month | W1: revenue
A2: CUST4474 | B2: Male | C2: 39 | D2: Mumbai | E2: Clothing | F2: 4 | G2: 4883 | H2: 19532 | I2: 45322 | J2: UPI | K2: =F2*G2 -> 19532 | L2: =IF(H2=K2,"Correct","Mismatch") -> Correct | M2: =IF(C2<20,"Teen",IF(C2<=40,"Adult","Senior")) -> Adult | N2: =IF(H2>10000,"High Value","Normal") -> High Value | O2: =TEXT(I2,"mmmm") -> January | Q2: =SUM(H:H) -> 1611742 | R2: =SUMIF(B:B,"Male",H:H) -> 789550 | S2: =SUMIF(B:B,"Female",H:H) -> 822192 | V2: January | W2: =SUMIF(O:O,O2,H:H) -> 135691
A3: CUST1518 | B3: Male | C3: 52 | D3: Delhi | E3: Clothing | F3: 2 | G3: 4463 | H3: 8926 | I3: 45611 | J3: Debit Card | K3: =F3*G3 -> 8926 | L3: =IF(H3=K3,"Correct","Mismatch") -> Correct | M3: =IF(C3<20,"Teen",IF(C3<=40,"Adult","Senior")) -> Senior | N3: =IF(H3>10000,"High Value","Normal") -> Normal | O3: =TEXT(I3,"mmmm") -> November | V3: February | W3: =SUMIF(O:O,O3,H:H) -> 99937
A4: CUST4175 | B4: Female | C4: 51 | D4: Delhi | E4: Sports | F4: 5 | G4: 2269 | H4: 11345 | I4: 45358 | J4: Cash | K4: =F4*G4 -> 11345 | L4: =IF(H4=K4,"Correct","Mismatch") -> Correct | M4: =IF(C4<20,"Teen",IF(C4<=40,"Adult","Senior")) -> Senior | N4: =IF(H4>10000,"High Value","Normal") -> High Value | O4: =TEXT(I4,"mmmm") -> March | V4: March | W4: =SUMIF(O:O,O4,H:H) -> 179507
A5: CUST7522 | B5: Female | C5: 33 | D5: Mumbai | E5: Electronics | F5: 2 | G5: 988 | H5: 1976 | I5: 45370 | J5: Credit Card | K5: =F5*G5 -> 1976 | L5: =IF(H5=K5,"Correct","Mismatch") -> Correct | M5: =IF(C5<20,"Teen",IF(C5<=40,"Adult","Senior")) -> Adult | N5: =IF(H5>10000,"High Value","Normal") -> Normal | O5: =TEXT(I5,"mmmm") -> March | Q5: REVENUE BY CATEGORY | V5: April | W5: =SUMIF(O:O,O5,H:H) -> 179507
A6: CUST4356 | B6: Male | C6: 50 | D6: Bangalore | E6: Sports | F6: 2 | G6: 4645 | H6: 9290 | I6: 45590 | J6: UPI | K6: =F6*G6 -> 9290 | L6: =IF(H6=K6,"Correct","Mismatch") -> Correct | M6: =IF(C6<20,"Teen",IF(C6<=40,"Adult","Senior")) -> Senior | N6: =IF(H6>10000,"High Value","Normal") -> Normal | O6: =TEXT(I6,"mmmm") -> October | Q6: Electronics | R6: CLOTHING | S6: SPORT | T6: HOME | V6: May | W6: =SUMIF(O:O,O6,H:H) -> 149653
A7: CUST1337 | B7: Female | C7: 50 | D7: Chennai | E7: Electronics | F7: 4 | G7: 4541 | H7: 18164 | I7: 45369 | J7: Credit Card | K7: =F7*G7 -> 18164 | L7: =IF(H7=K7,"Correct","Mismatch") -> Correct | M7: =IF(C7<20,"Teen",IF(C7<=40,"Adult","Senior")) -> Senior | N7: =IF(H7>10000,"High Value","Normal") -> High Value | O7: =TEXT(I7,"mmmm") -> March | Q7: =SUMIF(E:E,"Electronics",H:H) -> 425923 | R7: =SUMIF(E:E,"Clothing",H:H) -> 355920 | S7: =SUMIF(E:E,"Sports",H:H) -> 380509 | T7: =SUMIF(E:E,"Home",H:H) -> 449390 | V7: June | W7: =SUMIF(O:O,O7,H:H) -> 179507
A8: CUST5763 | B8: Female | C8: 27 | D8: Delhi | E8: Sports | F8: 1 | G8: 4468 | H8: 4468 | I8: 45600 | J8: UPI | K8: =F8*G8 -> 4468 | L8: =IF(H8=K8,"Correct","Mismatch") -> Correct | M8: =IF(C8<20,"Teen",IF(C8<=40,"Adult","Senior")) -> Adult | N8: =IF(H8>10000,"High Value","Normal") -> Normal | O8: =TEXT(I8,"mmmm") -> November | V8: July | W8: =SUMIF(O:O,O8,H:H) -> 99937
A9: CUST8124 | B9: Male | C9: 22 | D9: Mumbai | E9: Home | F9: 5 | G9: 4988 | H9: 24940 | I9: 45474 | J9: Cash | K9: =F9*G9 -> 24940 | L9: =IF(H9=K9,"Correct","Mismatch") -> Correct | M9: =IF(C9<20,"Teen",IF(C9<=40,"Adult","Senior")) -> Adult | N9: =IF(H9>10000,"High Value","Normal") -> High Value | O9: =TEXT(I9,"mmmm") -> July | V9: august | W9: =SUMIF(O:O,O9,H:H) -> 131113
A10: CUST7206 | B10: Male | C10: 41 | D10: Bangalore | E10: Sports | F10: 2 | G10: 3838 | H10: 7676 | I10: 45299 | J10: UPI | K10: =F10*G10 -> 7676 | L10: =IF(H10=K10,"Correct","Mismatch") -> Correct | M10: =IF(C10<20,"Teen",IF(C10<=40,"Adult","Senior")) -> Senior | N10: =IF(H10>10000,"High Value","Normal") -> Normal | O10: =TEXT(I10,"mmmm") -> January | V10: september | W10: =SUMIF(O:O,O10,H:H) -> 135691
A11: CUST7771 | B11: Male | C11: 46 | D11: Bangalore | E11: Electronics | F11: 2 | G11: 2043 | H11: 4086 | I11: 45391 | J11: UPI | K11: =F11*G11 -> 4086 | L11: =IF(H11=K11,"Correct","Mismatch") -> Correct | M11: =IF(C11<20,"Teen",IF(C11<=40,"Adult","Senior")) -> Senior | N11: =IF(H11>10000,"High Value","Normal") -> Normal | O11: =TEXT(I11,"mmmm") -> April | V11: october | W11: =SUMIF(O:O,O11,H:H) -> 79012
A12: CUST9361 | B12: Male | C12: 50 | D12: Chennai | E12: Electronics | F12: 2 | G12: 967 | H12: 1934 | I12: 45560 | J12: Credit Card | K12: =F12*G12 -> 1934 | L12: =IF(H12=K12,"Correct","Mismatch") -> Correct | M12: =IF(C12<20,"Teen",IF(C12<=40,"Adult","Senior")) -> Senior | N12: =IF(H12>10000,"High Value","Normal") -> Normal | O12: =TEXT(I12,"mmmm") -> September | V12: November | W12: =SUMIF(O:O,O12,H:H) -> 158620
A13: CUST4670 | B13: Female | C13: 51 | D13: Mumbai | E13: Clothing | F13: 3 | G13: 4223 | H13: 12669 | I13: 45474 | J13: Debit Card | K13: =F13*G13 -> 12669 | L13: =IF(H13=K13,"Correct","Mismatch") -> Correct | M13: =IF(C13<20,"Teen",IF(C13<=40,"Adult","Senior")) -> Senior | N13: =IF(H13>10000,"High Value","Normal") -> High Value | O13: =TEXT(I13,"mmmm") -> July | V13: December | W13: =SUMIF(O:O,O13,H:H) -> 131113
A14: CUST1216 | B14: Female | C14: 45 | D14: Delhi | E14: Sports | F14: 4 | G14: 1807 | H14: 7228 | I14: 45400 | J14: Debit Card | K14: =F14*G14 -> 7228 | L14: =IF(H14=K14,"Correct","Mismatch") -> Correct | M14: =IF(C14<20,"Teen",IF(C14<=40,"Adult","Senior")) -> Senior | N14: =IF(H14>10000,"High Value","Normal") -> Normal | O14: =TEXT(I14,"mmmm") -> April
A15: CUST5655 | B15: Female | C15: 32 | D15: Delhi | E15: Clothing | F15: 1 | G15: 777 | H15: 777 | I15: 45537 | J15: Credit Card | K15: =F15*G15 -> 777 | L15: =IF(H15=K15,"Correct","Mismatch") -> Correct | M15: =IF(C15<20,"Teen",IF(C15<=40,"Adult","Senior")) -> Adult | N15: =IF(H15>10000,"High Value","Normal") -> Normal | O15: =TEXT(I15,"mmmm") -> September
A16: CUST5932 | B16: Male | C16: 40 | D16: Bangalore | E16: Sports | F16: 1 | G16: 3681 | H16: 3681 | I16: 45297 | J16: Credit Card | K16: =F16*G16 -> 3681 | L16: =IF(H16=K16,"Correct","Mismatch") -> Correct | M16: =IF(C16<20,"Teen",IF(C16<=40,"Adult","Senior")) -> Adult | N16: =IF(H16>10000,"High Value","Normal") -> Normal | O16: =TEXT(I16,"mmmm") -> January
A17: CUST5284 | B17: Female | C17: 20 | D17: Delhi | E17: Home | F17: 4 | G17: 589 | H17: 2356 | I17: 45484 | J17: Debit Card | K17: =F17*G17 -> 2356 | L17: =IF(H17=K17,"Correct","Mismatch") -> Correct | M17: =IF(C17<20,"Teen",IF(C17<=40,"Adult","Senior")) -> Adult | N17: =IF(H17>10000,"High Value","Normal") -> Normal | O17: =TEXT(I17,"mmmm") -> July
A18: CUST5380 | B18: Male | C18: 19 | D18: Mumbai | E18: Home | F18: 4 | G18: 4247 | H18: 16988 | I18: 45657 | J18: UPI | K18: =F18*G18 -> 16988 | L18: =IF(H18=K18,"Correct","Mismatch") -> Correct | M18: =IF(C18<20,"Teen",IF(C18<=40,"Adult","Senior")) -> Teen | N18: =IF(H18>10000,"High Value","Normal") -> High Value | O18: =TEXT(I18,"mmmm") -> December
A19: CUST4914 | B19: Female | C19: 20 | D19: Bangalore | E19: Electronics | F19: 4 | G19: 2059 | H19: 8236 | I19: 45308 | J19: Cash | K19: =F19*G19 -> 8236 | L19: =IF(H19=K19,"Correct","Mismatch") -> Correct | M19: =IF(C19<20,"Teen",IF(C19<=40,"Adult","Senior")) -> Adult | N19: =IF(H19>10000,"High Value","Normal") -> Normal | O19: =TEXT(I19,"mmmm") -> January
A20: CUST8257 | B20: Male | C20: 35 | D20: Bangalore | E20: Sports | F20: 4 | G20: 1147 | H20: 4588 | I20: 45640 | J20: Cash | K20: =F20*G20 -> 4588 | L20: =IF(H20=K20,"Correct","Mismatch") -> Correct | M20: =IF(C20<20,"Teen",IF(C20<=40,"Adult","Senior")) -> Adult | N20: =IF(H20>10000,"High Value","Normal") -> Normal | O20: =TEXT(I20,"mmmm") -> December
A21: CUST5042 | B21: Male | C21: 54 | D21: Bangalore | E21: Sports | F21: 2 | G21: 3986 | H21: 7972 | I21: 45594 | J21: Debit Card | K21: =F21*G21 -> 7972 | L21: =IF(H21=K21,"Correct","Mismatch") -> Correct | M21: =IF(C21<20,"Teen",IF(C21<=40,"Adult","Senior")) -> Senior | N21: =IF(H21>10000,"High Value","Normal") -> Normal | O21: =TEXT(I21,"mmmm") -> October
A22: CUST2197 | B22: Male | C22: 56 | D22: Mumbai | E22: Electronics | F22: 2 | G22: 2626 | H22: 5252 | I22: 45558 | J22: Credit Card | K22: =F22*G22 -> 5252 | L22: =IF(H22=K22,"Correct","Mismatch") -> Correct | M22: =IF(C22<20,"Teen",IF(C22<=40,"Adult","Senior")) -> Senior | N22: =IF(H22>10000,"High Value","Normal") -> Normal | O22: =TEXT(I22,"mmmm") -> September
A23: CUST1235 | B23: Female | C23: 20 | D23: Mumbai | E23: Clothing | F23: 5 | G23: 1817 | H23: 9085 | I23: 45333 | J23: Credit Card | K23: =F23*G23 -> 9085 | L23: =IF(H23=K23,"Correct","Mismatch") -> Correct | M23: =IF(C23<20,"Teen",IF(C23<=40,"Adult","Senior")) -> Adult | N23: =IF(H23>10000,"High Value","Normal") -> Normal | O23: =TEXT(I23,"mmmm") -> February
A24: CUST1864 | B24: Male | C24: 22 | D24: Bangalore | E24: Clothing | F24: 5 | G24: 4238 | H24: 21190 | I24: 45567 | J24: Debit Card | K24: =F24*G24 -> 21190 | L24: =IF(H24=K24,"Correct","Mismatch") -> Correct | M24: =IF(C24<20,"Teen",IF(C24<=40,"Adult","Senior")) -> Adult | N24: =IF(H24>10000,"High Value","Normal") -> High Value | O24: =TEXT(I24,"mmmm") -> October
A25: CUST8206 | B25: Female | C25: 21 | D25: Chennai | E25: Home | F25: 5 | G25: 2410 | H25: 12050 | I25: 45418 | J25: UPI | K25: =F25*G25 -> 12050 | L25: =IF(H25=K25,"Correct","Mismatch") -> Correct | M25: =IF(C25<20,"Teen",IF(C25<=40,"Adult","Senior")) -> Adult | N25: =IF(H25>10000,"High Value","Normal") -> High Value | O25: =TEXT(I25,"mmmm") -> May
... A201: CUST3714 | B201: Male | C201: 58 | D201: Chennai | E201: Sports | F201: 4 | G201: 3542 | H201: 14168 | I201: 45506 | J201: Cash | K201: =F201*G201 -> 14168 | L201: =IF(H201=K201,"Correct","Mismatch") -> Correct | M201: =IF(C201<20,"Teen",IF(C201<=40,"Adult","Senior")) -> Senior | N201: =IF(H201>10000,"High Value","Normal") -> High Value | O201: =TEXT(I201,"mmmm") -> August
K202: =F202*G202 -> 0

Sheet GRAPH
A1: Total Revenue | B1: =SUM(Raw_Data!H2:H201) -> 1611742
A3: Revenue by Gender
A4: Male | B4: =SUMIF(Raw_Data!B2:B201,"Male",Raw_Data!H2:H201) -> 789550
A5: Female | B5: =SUMIF(Raw_Data!B2:B201,"Female",Raw_Data!H2:H201) -> 822192
A7: Revenue by Category
A8: Electronics | B8: =SUMIF(Raw_Data!E2:E201,"Electronics",Raw_Data!H2:H201) -> 425923
A9: Clothing | B9: =SUMIF(Raw_Data!E2:E201,"Clothing",Raw_Data!H2:H201) -> 355920
A10: Home | B10: =SUMIF(Raw_Data!E2:E201,"Home",Raw_Data!H2:H201) -> 449390
A11: Sports | B11: =SUMIF(Raw_Data!E2:E201,"Sports",Raw_Data!H2:H201) -> 380509
A20: month | B20: revenue
A21: January | B21: 135691
A22: February | B22: 99937
A23: March | B23: 179507
A24: April | B24: 179507
A25: May | B25: 149653 | S25: COUNT TRANSACTION BY PAYMENT
A26: June | B26: 179507 | S26: UPI | T26: CR CARD
A27: July | B27: 99937 | S27: =COUNTIF(Raw_Data!J:J,"UPI") -> 57 | T27: =COUNTIF(Raw_Data!J:J,"Credit Card") -> 48
A28: august | B28: 131113
A29: september | B29: 135691
A30: october | B30: 79012
A31: November | B31: 158620
A32: December | B32: 131113
A41: Male Revenue | B41: female revenu
A42: 789550 | B42: 822192
